fen2image/BoardRepresentation.py
fen2image/Fen.py
fen2image/__init__.py
fen2image/constants.py
fen2image/core.py
fen2image/utils.py
fen2image-1.0.1.dist-info/licenses/LICENSE
tests/test_board_representation.py
tests/test_fen.py
fen2image-1.0.1.dist-info/METADATA
fen2image-1.0.1.dist-info/WHEEL
fen2image-1.0.1.dist-info/top_level.txt
fen2image-1.0.1.dist-info/RECORD
