Metadata-Version: 2.4
Name: fen2image
Version: 1.0.1
Summary: Convert chess FEN strings to PIL Image
Author-email: Théo Gueuret <tgueuret@live.fr>
Requires-Python: >=3.7
License-File: LICENSE
Requires-Dist: pillow
Dynamic: license-file
